LICENSE
MANIFEST.in
README.md
setup.py
curvefitting/GUI.py
curvefitting/__init__.py
curvefitting/fit.py
curvefitting.egg-info/PKG-INFO
curvefitting.egg-info/SOURCES.txt
curvefitting.egg-info/dependency_links.txt
curvefitting.egg-info/requires.txt
curvefitting.egg-info/top_level.txt
curvefitting/language/MainWindow_en.qm
curvefitting/language/MainWindow_zh_CN.qm
curvefitting/language/about_en.qm
curvefitting/language/about_zh_CN.qm
curvefitting/language/help_en.qm
curvefitting/language/help_zh_CN.qm
curvefitting/language/input_en.qm
curvefitting/language/input_zh_CN.qm
curvefitting/ui/MainWindow.py
curvefitting/ui/about.py
curvefitting/ui/help.py
curvefitting/ui/input.py
curvefitting/ui/resource_rc.py