Metadata-Version: 2.1
Name: curvefitting
Version: 1.0.1
Summary: A MATLAB-like graphical curve fitting tool
Home-page: https://github.com/Hamlet-Fansion/curvefitting
Author: Fan Peilin
Author-email: fanpeilin123@126.com
License: MIT Licence
Keywords: pip,curvefitting,cftool,curve fitting tool,curve-fit
Platform: any
Classifier: Topic :: Software Development :: Libraries :: Python Modules
Classifier: Programming Language :: Python
Classifier: Programming Language :: Python :: 3
Classifier: Programming Language :: Python :: 3.6
Classifier: Programming Language :: Python :: 3.7
Classifier: Programming Language :: Python :: 3.8
Classifier: Programming Language :: Python :: Implementation :: CPython
